wen_mint/__init__.py
wen_mint/__version__.py
wen_mint/cli.py
wen_mint/external_scripts/_PRAW_refresh_token.py
wen_mint/external_scripts/__init__.py
wen_mint/utils/__init__.py
wen_mint/utils/_api_conn.py
wen_mint/utils/_config_io.py
wen_mint/utils/_extract_addresses.py
wen_mint-0.2.2.dist-info/LICENSE
wen_mint-0.2.2.dist-info/METADATA
wen_mint-0.2.2.dist-info/WHEEL
wen_mint-0.2.2.dist-info/entry_points.txt
wen_mint-0.2.2.dist-info/top_level.txt
wen_mint-0.2.2.dist-info/zip-safe
wen_mint-0.2.2.dist-info/RECORD
